h5massembly/__init__.py
h5massembly/assembly.py
h5massembly/assemblymesher.py
h5massembly/assemblymesher_cq.py
h5massembly/assemblymesher_gmsh.py
h5massembly/object_factory.py
h5massembly-0.0.12.dist-info/LICENSE
h5massembly-0.0.12.dist-info/METADATA
h5massembly-0.0.12.dist-info/WHEEL
h5massembly-0.0.12.dist-info/top_level.txt
h5massembly-0.0.12.dist-info/RECORD
