Metadata-Version: 2.1
Name: h5massembly
Version: 0.0.12
Summary: Package to automagically convert step-gometries to h5m descriptions for neutronics by OpenMC
Author-email: Erik B Knudsen <erik.knudsen@copenhagenatomics.com>
Project-URL: Homepage, https://github.com/openmsr/step_to_h5m
Project-URL: Bug Tracker, https://github.com/openmsr/step_to_h5m/issues
Classifier: Programming Language :: Python :: 3
Classifier: License :: OSI Approved :: MIT License
Classifier: Operating System :: OS Independent
Requires-Python: >=3.8
License-File: LICENSE
Requires-Dist: gmsh
Requires-Dist: cadquery2
Requires-Dist: numpy
Requires-Dist: OCP
Requires-Dist: meshio
Requires-Dist: trimesh
Requires-Dist: Cython
